{
    "quantidade_por_data": {
        "19/09/2023": 10,
        "09/2023": 151,
        "2023": 185,
        "06/09/2023": 4,
        "29/09/2023": 7,
        "03/10/2023": 7,
        "10/2023": 34,
        "16/09/2023": 3,
        "23/09/2023": 2,
        "27/09/2023": 13,
        "02/10/2023": 25,
        "20/09/2023": 6,
        "17/09/2023": 2,
        "14/09/2023": 9,
        "21/09/2023": 5,
        "24/09/2023": 2,
        "13/09/2023": 12,
        "07/09/2023": 11,
        "11/09/2023": 7,
        "18/09/2023": 6,
        "12/09/2023": 6,
        "22/09/2023": 5,
        "25/09/2023": 9,
        "08/09/2023": 4,
        "28/09/2023": 5,
        "10/09/2023": 1,
        "05/09/2023": 7,
        "26/09/2023": 5,
        "15/09/2023": 3,
        "30/09/2023": 1,
        "04/09/2023": 6,
        "01/01/1970": 1,
        "01/1970": 1,
        "1970": 1,
        "01/10/2023": 2
    },
    "quantidade_por_fonte_e_autor": {
        "source": {
            "Phys.Org": 24,
            "Science Daily": 24,
            "Pansci.asia": 7,
            "New Atlas": 6,
            "New Scientist": 6,
            "BBC News": 5,
            "ABC News": 5,
            "Gizmodo.jp": 4,
            "Business Insider": 4,
            "Yahoo Entertainment": 4,
            "Wired": 3,
            "Scientific American": 3,
            "Die Zeit": 3,
            "heise online": 3,
            "Time": 3,
            "Futurity: Research News": 3,
            "Slashdot.org": 3,
            "Engadget": 3,
            "Gizmodo.com": 3,
            "HuffPost": 2,
            "Boing Boing": 2,
            "NPR": 2,
            "Live Science": 2,
            "Ilfattoquotidiano.it": 2,
            "Olhardigital.com.br": 2,
            "TMZ": 2,
            "Ars Technica": 2,
            "Wired.jp": 1,
            "Spidersweb.pl": 1,
            "Asahi.com": 1,
            "Geekpark.net": 1,
            "Al Jazeera English": 1,
            "ABC News (AU)": 1,
            "Xataka.com": 1,
            "Royal Society of Chemistry": 1,
            "Il Sole 24 Ore": 1,
            "menshealth.com": 1,
            "Los Angeles Times": 1,
            "Thebridge.jp": 1,
            "Gendai.media": 1,
            "MedCity News": 1,
            "Focus": 1,
            "ANSA.it": 1,
            "Internazionale.it": 1,
            "DIE WELT": 1,
            "CBS News": 1,
            "taz.de": 1,
            "Sputnikglobe.com": 1,
            "Zoomit.ir": 1,
            "Abril.com.br": 1,
            "Technews.tw": 1,
            "EFF": 1,
            "Sciencebasedmedicine.org": 1,
            "Sacramento Bee": 1,
            "VentureBeat": 1,
            "The Verge": 1,
            "The Next Web": 1,
            "EurekAlert": 1,
            "Insideprecisionmedicine.com": 1,
            "Buzzfeed": 1,
            "Digital Trends": 1,
            "Basqu.es": 1,
            "Bioengineer.org": 1,
            "Wikipedia.org": 1,
            "Universe Today": 1,
            "The Intercept": 1,
            "Marginalrevolution.com": 1,
            "Biztoc.com": 1,
            "The Atlantic": 1,
            "The-sun.com": 1,
            "[Removed]": 1,
            "Abduzeedo.com": 1,
            "Slate Magazine": 1,
            "National Institutes of Health": 1,
            "TechRadar": 1,
            "BGR": 1,
            "Michaelchimenti.com": 1,
            "Nobelprize.org": 1,
            "Northwestern.edu": 1,
            "Srad.jp": 1,
            "VOA News": 1
        },
        "author": {
            "Science X": 13,
            "ZEIT ONLINE: News -": 3,
            "The Associated Press": 3,
            "https://www.facebook.com/bbcnews": 3,
            "Paul McClure": 3,
            "David Pescovitz": 2,
            "Michael Le Page": 2,
            "TMZ Staff": 2,
            "Karmela Padavic-Callaghan": 2,
            "msmash": 2,
            "Melissa Healy": 2,
            "Michael Irving": 2,
            "Andrew Tarantola": 2,
            "Isaac Schultz": 2,
            "PanSci": 2,
            "Veronika Szentpetery-Kessler": 2,
            "\u671d\u65e5\u65b0\u805e\u30c7\u30b8\u30bf\u30eb": 1,
            "Javier Jim\u00e9nez": 1,
            "Rafa\u0142 Dadura": 1,
            "Stephanie Pappas": 1,
            "30science per Il Fatto": 1,
            "\u7814\u4e4b\u6709\u7269\u2502\u4e2d\u592e\u7814\u7a76\u9662": 1,
            "Al Jazeera": 1,
            "Amit Katwala": 1,
            "Ann-Kathrin Leclere": 1,
            "Greg Williams-NYU": 1,
            "Asher Jones-U. Pittsburgh": 1,
            "Odelia Tepper, Hongchao Zheng, Daniel H. Appella, Eylon Yavin": 1,
            "Caitlin Sedwick": 1,
            "Steven Novella": 1,
            "LaTina Emerson-Georgia State": 1,
            "prnewswire.com": 1,
            "nagazou": 1,
            "Liu Jia": 1,
            "Sam Sholtis": 1,
            "": 1,
            "Lauren J. Young": 1,
            "Jason Arunn Murugesu": 1,
            "VentureBeat": 1,
            "di Francesca Cerati": 1,
            "Daisuke Takimoto": 1,
            "Hanan Dervisevic": 1,
            "Chimauchem  Nwosu": 1,
            "Robert Langreth": 1,
            "Diogo Sponchiato": 1,
            "Darren Orf": 1,
            "F. Q.": 1,
            "\u0645\u0631\u06cc\u0645 \u0635\u0641\u062f\u0631\u06cc": 1,
            "Will Dunham": 1,
            "Ben Coxworth": 1,
            "\u96c5\u6587\u5152\u7ae5\u807d\u8a9e\u6587\u6559\u57fa\u91d1\u6703": 1,
            "\u81c9\u8b5c\u51fa\u7248": 1,
            "\u9ec3 \u5b3f": 1,
            "careonline": 1,
            "\u9ce5\u82f7\u4e09\u78f7\u9178 (PanSci Promo)": 1,
            "Donavyn Coffey": 1,
            "CBS News": 1,
            "Edda Grabar": 1,
            "Internazionale": 1,
            "Alessandro Di Lorenzo": 1,
            "FOCUS online": 1,
            "FRANK VINLUAN - MEDCITY NEWS": 1,
            "mchimen1": 1,
            "Pedro Borges Spadoni": 1,
            "\u5ca9\u7530\u30ea\u30e7\u30a6\u30b3": 1,
            "Jen\u00e9e Desmond-Harris": 1,
            "Joshua Hawkins": 1,
            "STEVE LeBLANC": 1,
            "\u5ca1\u672c\u7384\u4ecb": 1,
            "Jenny McGrath": 1,
            "AP": 1,
            "Bob Yirka": 1,
            "Ajani Bazile-Dutes": 1,
            "satomi": 1,
            "Jeanne Timmons": 1,
            "Brent D. Griffiths": 1,
            "Susanne Donner": 1,
            "Malorye Branca": 1,
            "Charlotte Alter": 1,
            "Naomi Oreskes": 1,
            "Alice Park": 1,
            "SEAN MURPHY Associated Press": 1,
            "Megan Farokhmanesh": 1,
            "Ioanna Lykiardopoulou": 1,
            "Ramin Skibba": 1,
            "Charles R. Davis": 1,
            "Jennifer Pattison Tuohy": 1,
            "Beth Mole": 1,
            "Cheryl Eddy": 1,
            "EditorDavid": 1,
            "Louis Columbus": 1,
            "Will Shanklin": 1,
            "Kim Krieger": 1,
            "Elizabeth Rayne": 1,
            "Leo DeLuca": 1,
            "Daniella Segura": 1,
            "desire.athow@futurenet.com (Desire Athow)": 1,
            "Tom Major, Axel Barlow, Wolfgang W\u00fcster": 1,
            "Saira Hussain, Matthew Guariglia": 1,
            "abduzeedo": 1,
            "Israel Salas-Rodriguez": 1,
            "Isabel Fattal": 1,
            "Peter R\u00fcegg": 1,
            "Heidi Opdyke": 1,
            "Michelle Klampe": 1,
            "Tyler Cowen": 1,
            "GARY D. ROBERTSON / AP": 1,
            "Insider Inc.": 1,
            "Briley Kenney": 1,
            "Liliana Segura": 1,
            "Tonya Mosley": 1,
            "Silvia Cernea Clark": 1,
            "Evan Gough": 1,
            "Contributors to Wikimedia projects": 1,
            "GERALD IMRAY Associated Press": 1,
            "Rina Fukazu": 1,
            "ANDREW SELSKY Associated Press": 1,
            "Bioengineer": 1,
            "Krisy Gashler": 1,
            "Marco Margaritoff": 1,
            "VOA Learning English": 1
        }
    },
    "quantidade_por_palavra_chave": {
        "dna": {
            "Quantidade por dia": {
                "25/09/2023": 4,
                "05/09/2023": 3,
                "04/09/2023": 3,
                "27/09/2023": 3,
                "29/09/2023": 3,
                "20/09/2023": 2,
                "26/09/2023": 2,
                "18/09/2023": 2,
                "22/09/2023": 2,
                "13/09/2023": 2,
                "21/09/2023": 2,
                "14/09/2023": 1,
                "11/09/2023": 1,
                "15/09/2023": 1,
                "19/09/2023": 1,
                "02/10/2023": 1,
                "01/10/2023": 1,
                "06/09/2023": 1
            },
            "Quantidade por mes": {
                "09/2023": 33,
                "10/2023": 2
            },
            "Quantidade por ano": {
                "2023": 35
            }
        },
        "rna": {
            "Quantidade por dia": {
                "02/10/2023": 10,
                "27/09/2023": 5,
                "04/09/2023": 4,
                "19/09/2023": 4,
                "25/09/2023": 3,
                "13/09/2023": 3,
                "05/09/2023": 3,
                "22/09/2023": 3,
                "21/09/2023": 2,
                "20/09/2023": 2,
                "03/10/2023": 2,
                "07/09/2023": 2,
                "08/09/2023": 1,
                "01/10/2023": 1,
                "12/09/2023": 1,
                "11/09/2023": 1,
                "18/09/2023": 1,
                "24/09/2023": 1
            },
            "Quantidade por mes": {
                "09/2023": 36,
                "10/2023": 13
            },
            "Quantidade por ano": {
                "2023": 49
            }
        }
    }
}